weepy/__init__.py
weepy/asgi.py
weepy/request.py
weepy/response.py
weepy/route.py
weepy-1.2.0.data/scripts/asgi_dev.py
weepy-1.2.0.data/scripts/dev_server.py
weepy-1.2.0.dist-info/LICENSE
weepy-1.2.0.dist-info/METADATA
weepy-1.2.0.dist-info/WHEEL
weepy-1.2.0.dist-info/entry_points.txt
weepy-1.2.0.dist-info/top_level.txt
weepy-1.2.0.dist-info/RECORD
