Metadata-Version: 2.1
Name: weepy
Version: 1.2.0
Summary: Tiny ASGI framework
Home-page: https://gitlab.com/katry/weepy
Author: Patrik Katrenak
Author-email: patrik@katryapps.com
License: UNKNOWN
Platform: any
Classifier: Programming Language :: Python :: 3
Classifier: License :: OSI Approved :: GNU Lesser General Public License v3 (LGPLv3)
Classifier: Operating System :: OS Independent
Requires-Python: >=3.9
License-File: LICENSE
Requires-Dist: orjson
Provides-Extra: dev
Requires-Dist: python-daemon ; extra == 'dev'
Requires-Dist: python-dotenv ; extra == 'dev'
Requires-Dist: uvicorn[standard] ; extra == 'dev'
Requires-Dist: requests ; extra == 'dev'
Requires-Dist: pytest ; extra == 'dev'
